musconv/__init__.py
musconv/chkconv.py
musconv/supcgen.py
tests/__init__.py
tests/conftest.py
tests/test_chkconv.py
tests/test_supcgen.py
musconv-0.0.2.dist-info/LICENSE
musconv-0.0.2.dist-info/METADATA
musconv-0.0.2.dist-info/WHEEL
musconv-0.0.2.dist-info/top_level.txt
musconv-0.0.2.dist-info/RECORD
