Metadata-Version: 2.1
Name: musconv
Version: 0.0.2
Summary: Generate supercell and check supercell convergence with SCF forces
Home-page: https://github.com/positivemuon/musconv
Author: Ifeanyi John Onuorah
Author-email: 
License: MIT
Platform: UNKNOWN
Classifier: License :: OSI Approved :: MIT License
Classifier: Programming Language :: Python :: 3.8
Classifier: Operating System :: OS Independent
Classifier: Topic :: Scientific/Engineering :: Physics
Requires-Dist: pymatgen
Requires-Dist: ase
Requires-Dist: numpy
Requires-Dist: scipy
Requires-Dist: pymatgen-analysis-defects ; python_version >= "3.8"
